git_scrape.py
git_scrape-2020.1.31.1.dist-info/METADATA
git_scrape-2020.1.31.1.dist-info/WHEEL
git_scrape-2020.1.31.1.dist-info/entry_points.txt
git_scrape-2020.1.31.1.dist-info/top_level.txt
git_scrape-2020.1.31.1.dist-info/RECORD
