Metadata-Version: 2.1
Name: git-scrape
Version: 2020.1.31.1
Summary: UNKNOWN
Home-page: https://github.com/waynew/upgraded-octo-umbrella
Author: Wayne Werner
Author-email: wayne@waynewerner.com
License: UNKNOWN
Platform: UNKNOWN
Requires-Dist: quiz
Provides-Extra: build
Requires-Dist: wheel ; extra == 'build'
Provides-Extra: test
Requires-Dist: pytest ; extra == 'test'
